{
  "DefaultVoice": "en-US-AriaNeural",
  "Mappings": {
    "af": "af-ZA-AdriNeural",
    "sq": "sq-AL-AnilaNeural",
    "am": "am-ET-MekdesNeural",
    "ar": "ar-EG-SalmaNeural",
    "hy": "hy-AM-AnahitNeural",
    "az": "az-AZ-BabekNeural",
    "eu": "eu-ES-AinhoaNeural",
    "be": "be-BY-AntonNeural",
    "bn": "bn-IN-TanishaaNeural",
    "bs": "bs-BA-GoranNeural",
    "bg": "bg-BG-KalinaNeural",
    "ca": "ca-ES-JoanaNeural",
    "ceb": "fil-PH-BlessicaNeural",
    "ny": "ny-MW-ThokoNeural",
    "zh": "zh-CN-XiaoxiaoNeural",
    "zh-TW": "zh-TW-HsiaoChenNeural",
    "co": "co-FR-ColineNeural",
    "hr": "hr-HR-GabrijelaNeural",
    "cs": "cs-CZ-VlastaNeural",
    "da": "da-DK-ChristelNeural",
    "nl": "nl-NL-ColetteNeural",
    "en": "en-US-AriaNeural",
    "eo": "eo-EO-EmilioNeural",
    "et": "et-EE-AnuNeural",
    "tl": "fil-PH-BlessicaNeural",
    "fi": "fi-FI-NooraNeural",
    "fr": "fr-FR-DeniseNeural",
    "fy": "fy-NL-RiemerNeural",
    "gl": "gl-ES-SabelaNeural",
    "ka": "ka-GE-EkaNeural",
    "de": "de-DE-KatjaNeural",
    "el": "el-GR-AthinaNeural",
    "gu": "gu-IN-DhwaniNeural",
    "ht": "ht-HT-JosephNeural",
    "ha": "ha-NG-AminaNeural",
    "haw": "haw-US-KeoniNeural",
    "iw": "he-IL-HilaNeural",
    "hi": "hi-IN-SwaraNeural",
    "hmn": "hmn-US-MaiNeural",
    "hu": "hu-HU-NoemiNeural",
    "is": "is-IS-GudrunNeural",
    "ig": "ig-NG-NnekaNeural",
    "id": "id-ID-GadisNeural",
    "ga": "ga-IE-OrlaNeural",
    "it": "it-IT-ElsaNeural",
    "ja": "ja-JP-NanamiNeural",
    "jv": "jv-ID-DimasNeural",
    "kn": "kn-IN-SapnaNeural",
    "kk": "kk-KZ-AigulNeural",
    "km": "km-KH-SreymomNeural",
    "rw": "rw-RW-ClaudineNeural",
    "ko": "ko-KR-SunHiNeural",
    "ku": "ku-IQ-LewanNeural",
    "ky": "ky-KG-MadinaNeural",
    "lo": "lo-LA-KeomanyNeural",
    "la": "la-IT-FabiolaNeural",
    "lv": "lv-LV-EveritaNeural",
    "lt": "lt-LT-OnaNeural",
    "lb": "lb-LU-LauraNeural",
    "mk": "mk-MK-MarijaNeural",
    "mg": "mg-MG-TiaraNeural",
    "ms": "ms-MY-OsmanNeural",
    "ml": "ml-IN-SobhanaNeural",
    "mt": "mt-MT-GraceNeural",
    "mi": "mi-NZ-TeRangiNeural",
    "mr": "mr-IN-AarohiNeural",
    "mn": "mn-MN-BataaNeural",
    "my": "my-MM-NilarNeural",
    "ne": "ne-NP-HemkalaNeural",
    "no": "nb-NO-IselinNeural",
    "or": "or-IN-JhansiNeural",
    "ps": "ps-AF-LatifaNeural",
    "fa": "fa-IR-DilaraNeural",
    "pl": "pl-PL-AgnieszkaNeural",
    "pt": "pt-BR-FranciscaNeural",
    "pa": "pa-IN-GurpreetNeural",
    "ro": "ro-RO-AlinaNeural",
    "ru": "ru-RU-SvetlanaNeural",
    "sm": "sm-WS-LiufauNeural",
    "gd": "gd-GB-KirstyNeural",
    "sr": "sr-RS-SophieNeural",
    "st": "st-ZA-LeratoNeural",
    "sn": "sn-ZW-TadiwaNeural",
    "sd": "sd-PK-GulNawazNeural",
    "si": "si-LK-ThiliniNeural",
    "sk": "sk-SK-ViktoriaNeural",
    "sl": "sl-SI-PetraNeural",
    "so": "so-SO-MuuseNeural",
    "es": "es-ES-ElviraNeural",
    "su": "su-ID-JajangNeural",
    "sw": "sw-KE-ZuriNeural",
    "sv": "sv-SE-SofieNeural",
    "tg": "tg-TJ-SitoraNeural",
    "ta": "ta-IN-PallaviNeural",
    "tt": "tt-RU-AigulNeural",
    "te": "te-IN-ShrutiNeural",
    "th": "th-TH-AcharaNeural",
    "tr": "tr-TR-EmelNeural",
    "tk": "tk-TM-MyakhriNeural",
    "uk": "uk-UA-PolinaNeural",
    "ur": "ur-PK-AsadNeural",
    "ug": "ug-CN-GulnurNeural",
    "uz": "uz-UZ-MadinaNeural",
    "vi": "vi-VN-HoaiMyNeural",
    "cy": "cy-GB-NiaNeural",
    "xh": "xh-ZA-ThandoNeural",
    "yi": "yi-DE-ChavaNeural",
    "yo": "yo-NG-AdeolaNeural",
    "zu": "zu-ZA-ThandoNeural"
  }
}